{ "businesses": [ {
      "id": "mortys-delicatessen-san-francisco",
      "name": "Morty's Delicatessen",
      "image_url": "https://s3-media3.fl.yelpcdn.com/bphoto/-uy1qxUzlCHGLa8FUfm90w/o.jpg",
      "is_closed": false,
      "url": "https://www.yelp.com/biz/mortys-delicatessen-san-francisco?adjust_creative=TJCJBQCAAm_aB5D00Y6-UQ&utm_campaign=yelp_api_v3&utm_medium=api_v3_business_search&utm_source=TJCJBQCAAm_aB5D00Y6-UQ",
      "review_count": 490,
      "categories": [
          {
              "alias": "sandwiches",
              "title": "Sandwiches"
          },
          {
              "alias": "delis",
              "title": "Delis"
          },
          {
              "alias": "vegetarian",
              "title": "Vegetarian"
          }
      ],
      "rating": 4,
      "coordinates": {
          "latitude": 37.78188,
          "longitude": -122.41522
      },
      "transactions": [
          "delivery",
          "pickup"
      ],
      "price": "$",
      "location": {
          "address1": "280 Golden Gate Ave",
          "address2": null,
          "address3": "",
          "city": "San Francisco",
          "zip_code": "94102",
          "country": "US",
          "state": "CA",
          "display_address": [
              "280 Golden Gate Ave",
              "San Francisco, CA 94102"
          ]
      },
      "phone": "+14155673354",
      "display_phone": "(415) 567-3354",
      "distance": 1457.550913768033
  },
  {
      "id": "daniels-cafe-san-francisco-2",
      "name": "Daniel's Cafe",
      "image_url": "https://s3-media2.fl.yelpcdn.com/bphoto/bnGv8c7Ct2PoNE0FM3QLpQ/o.jpg",
      "is_closed": false,
      "url": "https://www.yelp.com/biz/daniels-cafe-san-francisco-2?adjust_creative=TJCJBQCAAm_aB5D00Y6-UQ&utm_campaign=yelp_api_v3&utm_medium=api_v3_business_search&utm_source=TJCJBQCAAm_aB5D00Y6-UQ",
      "review_count": 218,
      "categories": [
          {
              "alias": "coffee",
              "title": "Coffee & Tea"
          },
          {
              "alias": "bagels",
              "title": "Bagels"
          },
          {
              "alias": "delis",
              "title": "Delis"
          }
      ],
      "rating": 4,
      "coordinates": {
          "latitude": 37.7855284,
          "longitude": -122.4088907
      },
      "transactions": [],
      "price": "$",
      "location": {
          "address1": "154 Ellis St",
          "address2": "",
          "address3": "",
          "city": "San Francisco",
          "zip_code": "94102",
          "country": "US",
          "state": "CA",
          "display_address": [
              "154 Ellis St",
              "San Francisco, CA 94102"
          ]
      },
      "phone": "+14159561760",
      "display_phone": "(415) 956-1760",
      "distance": 802.6623727881846
  },
  {
      "id": "lucca-delicatessen-san-francisco",
      "name": "Lucca Delicatessen",
      "image_url": "https://s3-media2.fl.yelpcdn.com/bphoto/pu2AP6ampLBOlWkWBPlVBA/o.jpg",
      "is_closed": false,
      "url": "https://www.yelp.com/biz/lucca-delicatessen-san-francisco?adjust_creative=TJCJBQCAAm_aB5D00Y6-UQ&utm_campaign=yelp_api_v3&utm_medium=api_v3_business_search&utm_source=TJCJBQCAAm_aB5D00Y6-UQ",
      "review_count": 551,
      "categories": [
          {
              "alias": "delis",
              "title": "Delis"
          },
          {
              "alias": "sandwiches",
              "title": "Sandwiches"
          },
          {
              "alias": "cheese",
              "title": "Cheese Shops"
          }
      ],
      "rating": 4,
      "coordinates": {
          "latitude": 37.8007698059082,
          "longitude": -122.438385009766
      },
      "transactions": [
          "pickup"
      ],
      "price": "$",
      "location": {
          "address1": "2120 Chestnut St",
          "address2": "",
          "address3": "",
          "city": "San Francisco",
          "zip_code": "94123",
          "country": "US",
          "state": "CA",
          "display_address": [
              "2120 Chestnut St",
              "San Francisco, CA 94123"
          ]
      },
      "phone": "+14159217873",
      "display_phone": "(415) 921-7873",
      "distance": 3714.518723204903
  },
  {
      "id": "market-mayflower-and-deli-san-francisco",
      "name": "Market Mayflower & Deli",
      "image_url": "https://s3-media1.fl.yelpcdn.com/bphoto/mekkXctsflvuxgJBIM-1Ow/o.jpg",
      "is_closed": false,
      "url": "https://www.yelp.com/biz/market-mayflower-and-deli-san-francisco?adjust_creative=TJCJBQCAAm_aB5D00Y6-UQ&utm_campaign=yelp_api_v3&utm_medium=api_v3_business_search&utm_source=TJCJBQCAAm_aB5D00Y6-UQ",
      "review_count": 128,
      "categories": [
          {
              "alias": "grocery",
              "title": "Grocery"
          },
          {
              "alias": "delis",
              "title": "Delis"
          },
          {
              "alias": "markets",
              "title": "Fruits & Veggies"
          }
      ],
      "rating": 4.5,
      "coordinates": {
          "latitude": 37.789569,
          "longitude": -122.413516
      },
      "transactions": [],
      "price": "$$",
      "location": {
          "address1": "985 Bush St",
          "address2": "",
          "address3": "",
          "city": "San Francisco",
          "zip_code": "94109",
          "country": "US",
          "state": "CA",
          "display_address": [
              "985 Bush St",
              "San Francisco, CA 94109"
          ]
      },
      "phone": "+14157476110",
      "display_phone": "(415) 747-6110",
      "distance": 1227.1423477713013
  },
  {
      "id": "sf-deli-and-wine-san-francisco-3",
      "name": "SF Deli & Wine",
      "image_url": "https://s3-media3.fl.yelpcdn.com/bphoto/54PEA7BhYSnyTs3YqOxa5Q/o.jpg",
      "is_closed": false,
      "url": "https://www.yelp.com/biz/sf-deli-and-wine-san-francisco-3?adjust_creative=TJCJBQCAAm_aB5D00Y6-UQ&utm_campaign=yelp_api_v3&utm_medium=api_v3_business_search&utm_source=TJCJBQCAAm_aB5D00Y6-UQ",
      "review_count": 15,
      "categories": [
          {
              "alias": "beer_and_wine",
              "title": "Beer, Wine & Spirits"
          },
          {
              "alias": "delis",
              "title": "Delis"
          }
      ],
      "rating": 4,
      "coordinates": {
          "latitude": 37.7839431994157,
          "longitude": -122.405098485531
      },
      "transactions": [
          "pickup"
      ],
      "price": "$",
      "location": {
          "address1": "810 Mission St",
          "address2": "",
          "address3": "",
          "city": "San Francisco",
          "zip_code": "94103",
          "country": "US",
          "state": "CA",
          "display_address": [
              "810 Mission St",
              "San Francisco, CA 94103"
          ]
      },
      "phone": "+14155127847",
      "display_phone": "(415) 512-7847",
      "distance": 556.559132023059
  },
  {
      "id": "kama-o-deli-san-francisco",
      "name": "Kama O Deli",
      "image_url": "https://s3-media4.fl.yelpcdn.com/bphoto/fbZR4BqPc4Hc53hsigMRCg/o.jpg",
      "is_closed": false,
      "url": "https://www.yelp.com/biz/kama-o-deli-san-francisco?adjust_creative=TJCJBQCAAm_aB5D00Y6-UQ&utm_campaign=yelp_api_v3&utm_medium=api_v3_business_search&utm_source=TJCJBQCAAm_aB5D00Y6-UQ",
      "review_count": 55,
      "categories": [
          {
              "alias": "delis",
              "title": "Delis"
          },
          {
              "alias": "japanese",
              "title": "Japanese"
          }
      ],
      "rating": 4,
      "coordinates": {
          "latitude": 37.7801891062951,
          "longitude": -122.394493681462
      },
      "transactions": [
          "pickup"
      ],
      "price": "$$",
      "location": {
          "address1": "590 3rd St",
          "address2": "",
          "address3": "",
          "city": "San Francisco",
          "zip_code": "94107",
          "country": "US",
          "state": "CA",
          "display_address": [
              "590 3rd St",
              "San Francisco, CA 94107"
          ]
      },
      "phone": "+14158729622",
      "display_phone": "(415) 872-9622",
      "distance": 879.3405041678303
  }
]}